README.md
numa.py
setup.py
python_numa.egg-info/PKG-INFO
python_numa.egg-info/SOURCES.txt
python_numa.egg-info/dependency_links.txt
python_numa.egg-info/top_level.txt