Metadata-Version: 1.1
Name: python-numa
Version: 0.5
Summary: Python libnuma ctypes wrapper
Home-page: https://github.com/zakalibit/python-numa
Author: Alex Revetchi
Author-email: alex.revetchi@gmail.com
License: License :: OSI Approved :: MIT License
Platform: Linux
Classifier: Development Status :: 2 - Pre-Alpha
Classifier: Intended Audience :: Developers
Classifier: Intended Audience :: Information Technology
Classifier: Intended Audience :: System Administrators
Classifier: License :: OSI Approved :: MIT License
Classifier: Operating System :: POSIX
Classifier: Operating System :: POSIX :: Linux
Classifier: Programming Language :: Python
